text_to_graphql_mcp/__init__.py
text_to_graphql_mcp/agent.py
text_to_graphql_mcp/config.py
text_to_graphql_mcp/error_handlers.py
text_to_graphql_mcp/exceptions.py
text_to_graphql_mcp/logger.py
text_to_graphql_mcp/mcp_server.py
text_to_graphql_mcp/types.py
text_to_graphql_mcp/tools/__init__.py
text_to_graphql_mcp/tools/data_visualization.py
text_to_graphql_mcp/tools/graphql_helpers.py
text_to_graphql_mcp/tools/intent_options.py
text_to_graphql_mcp/tools/intent_recognition.py
text_to_graphql_mcp/tools/query_construction.py
text_to_graphql_mcp/tools/query_execution.py
text_to_graphql_mcp/tools/query_optimization.py
text_to_graphql_mcp/tools/query_validation.py
text_to_graphql_mcp/tools/schema_management.py
text_to_graphql_mcp/tools/select_options.py
text_to_graphql_mcp-0.1.3.dist-info/METADATA
text_to_graphql_mcp-0.1.3.dist-info/WHEEL
text_to_graphql_mcp-0.1.3.dist-info/entry_points.txt
text_to_graphql_mcp-0.1.3.dist-info/licenses/LICENSE
text_to_graphql_mcp-0.1.3.dist-info/RECORD
