Metadata-Version: 2.4
Name: text-to-graphql-mcp
Version: 0.1.3
Summary: Transform natural language queries into GraphQL queries using an MCP server
Project-URL: Homepage, https://github.com/Arize-ai/text-to-graphql-mcp/
Project-URL: Repository, https://github.com/Arize-ai/text-to-graphql-mcp/
Project-URL: Documentation, https://github.com/Arize-ai/text-to-graphql-mcp#readme
Author-email: Anthony Abercrombie <aabercrombie@arize.com>
Maintainer-email: Anthony Abercrombie <aabercrombie@arize.com>, John Gilhuly <john@arize.com>
License-Expression: LicenseRef-Elastic-2.0
License-File: LICENSE
Keywords: ai,graphql,langchain,langgraph,mcp,natural-language
Classifier: Development Status :: 3 - Alpha
Classifier: Intended Audience :: Developers
Classifier: Programming Language :: Python :: 3
Classifier: Programming Language :: Python :: 3.12
Classifier: Topic :: Internet :: WWW/HTTP :: Dynamic Content
Classifier: Topic :: Scientific/Engineering :: Artificial Intelligence
Classifier: Topic :: Software Development :: Libraries :: Python Modules
Requires-Python: >=3.10
Requires-Dist: fastapi>=0.101.0
Requires-Dist: fastmcp>=0.1.0
Requires-Dist: gql
Requires-Dist: graphql-core>=3.0.0
Requires-Dist: ipykernel>=6.0.0
Requires-Dist: jinja2>=3.1.2
Requires-Dist: langchain-openai>=0.0.2
Requires-Dist: langchain>=0.0.267
Requires-Dist: langgraph>=0.0.17
Requires-Dist: loguru
Requires-Dist: openai>=1.3.0
Requires-Dist: pydantic-settings
Requires-Dist: pydantic>=2.1.0
Requires-Dist: python-dotenv>=1.0.0
Requires-Dist: python-multipart>=0.0.6
Requires-Dist: requests>=2.31.0
Requires-Dist: termcolor
Requires-Dist: uvicorn>=0.23.0
Provides-Extra: dev
Requires-Dist: black>=23.0.0; extra == 'dev'
Requires-Dist: flake8>=6.0.0; extra == 'dev'
Requires-Dist: isort>=5.12.0; extra == 'dev'
Requires-Dist: mypy>=1.0.0; extra == 'dev'
Requires-Dist: pre-commit>=3.0.0; extra == 'dev'
Requires-Dist: pytest-asyncio>=0.21.0; extra == 'dev'
Requires-Dist: pytest-cov>=4.0.0; extra == 'dev'
Requires-Dist: pytest>=7.0.0; extra == 'dev'
Provides-Extra: docs
Requires-Dist: mkdocs-material>=9.0.0; extra == 'docs'
Requires-Dist: mkdocs>=1.5.0; extra == 'docs'
Requires-Dist: mkdocstrings[python]>=0.23.0; extra == 'docs'
